{
  "version": "6",
  "dialect": "sqlite",
  "id": "f3d28219-4ea9-4b34-8981-d4851c7ef280",
  "prevId": "f58f726f-545d-450a-8fb6-372e3a40f971",
  "tables": {
    "settings": {
      "name": "settings",
      "columns": {
        "key": {
          "name": "key",
          "type": "text",
          "primaryKey": true,
          "notNull": true,
          "autoincrement": false
        },
        "value": {
          "name": "value",
          "type": "text",
          "primaryKey": false,
          "notNull": true,
          "autoincrement": false
        },
        "updated_at": {
          "name": "updated_at",
          "type": "integer",
          "primaryKey": false,
          "notNull": true,
          "autoincrement": false
        }
      },
      "indexes": {},
      "foreignKeys": {},
      "compositePrimaryKeys": {},
      "uniqueConstraints": {},
      "checkConstraints": {}
    },
    "questions": {
      "name": "questions",
      "columns": {
        "id": {
          "name": "id",
          "type": "integer",
          "primaryKey": true,
          "notNull": true,
          "autoincrement": true
        },
        "context": {
          "name": "context",
          "type": "text",
          "primaryKey": false,
          "notNull": true,
          "autoincrement": false,
          "default": "'onboarding'"
        },
        "key": {
          "name": "key",
          "type": "text",
          "primaryKey": false,
          "notNull": true,
          "autoincrement": false
        },
        "order": {
          "name": "order",
          "type": "integer",
          "primaryKey": false,
          "notNull": true,
          "autoincrement": false
        },
        "type": {
          "name": "type",
          "type": "text",
          "primaryKey": false,
          "notNull": true,
          "autoincrement": false
        },
        "category": {
          "name": "category",
          "type": "text",
          "primaryKey": false,
          "notNull": true,
          "autoincrement": false
        },
        "question_text": {
          "name": "question_text",
          "type": "text",
          "primaryKey": false,
          "notNull": true,
          "autoincrement": false
        },
        "required": {
          "name": "required",
          "type": "integer",
          "primaryKey": false,
          "notNull": true,
          "autoincrement": false,
          "default": true
        },
        "depends_on_question_key": {
          "name": "depends_on_question_key",
          "type": "text",
          "primaryKey": false,
          "notNull": false,
          "autoincrement": false
        },
        "depends_on_value": {
          "name": "depends_on_value",
          "type": "text",
          "primaryKey": false,
          "notNull": false,
          "autoincrement": false
        },
        "metadata": {
          "name": "metadata",
          "type": "text",
          "primaryKey": false,
          "notNull": false,
          "autoincrement": false
        },
        "created_at": {
          "name": "created_at",
          "type": "integer",
          "primaryKey": false,
          "notNull": true,
          "autoincrement": false
        }
      },
      "indexes": {
        "questions_context_key_unique": {
          "name": "questions_context_key_unique",
          "columns": [
            "context",
            "key"
          ],
          "isUnique": true
        }
      },
      "foreignKeys": {},
      "compositePrimaryKeys": {},
      "uniqueConstraints": {},
      "checkConstraints": {}
    },
    "question_answers": {
      "name": "question_answers",
      "columns": {
        "id": {
          "name": "id",
          "type": "integer",
          "primaryKey": true,
          "notNull": true,
          "autoincrement": true
        },
        "context": {
          "name": "context",
          "type": "text",
          "primaryKey": false,
          "notNull": true,
          "autoincrement": false
        },
        "question_key": {
          "name": "question_key",
          "type": "text",
          "primaryKey": false,
          "notNull": true,
          "autoincrement": false
        },
        "user_id": {
          "name": "user_id",
          "type": "integer",
          "primaryKey": false,
          "notNull": false,
          "autoincrement": false
        },
        "answer": {
          "name": "answer",
          "type": "text",
          "primaryKey": false,
          "notNull": true,
          "autoincrement": false
        },
        "answered_at": {
          "name": "answered_at",
          "type": "integer",
          "primaryKey": false,
          "notNull": true,
          "autoincrement": false
        },
        "updated_at": {
          "name": "updated_at",
          "type": "integer",
          "primaryKey": false,
          "notNull": true,
          "autoincrement": false
        }
      },
      "indexes": {
        "question_answers_context_key_unique": {
          "name": "question_answers_context_key_unique",
          "columns": [
            "context",
            "question_key"
          ],
          "isUnique": true
        }
      },
      "foreignKeys": {},
      "compositePrimaryKeys": {},
      "uniqueConstraints": {},
      "checkConstraints": {}
    },
    "users": {
      "name": "users",
      "columns": {
        "id": {
          "name": "id",
          "type": "integer",
          "primaryKey": true,
          "notNull": true,
          "autoincrement": true
        },
        "coins": {
          "name": "coins",
          "type": "integer",
          "primaryKey": false,
          "notNull": true,
          "autoincrement": false,
          "default": 0
        },
        "created_at": {
          "name": "created_at",
          "type": "integer",
          "primaryKey": false,
          "notNull": true,
          "autoincrement": false
        }
      },
      "indexes": {},
      "foreignKeys": {},
      "compositePrimaryKeys": {},
      "uniqueConstraints": {},
      "checkConstraints": {}
    },
    "coin_transactions": {
      "name": "coin_transactions",
      "columns": {
        "id": {
          "name": "id",
          "type": "integer",
          "primaryKey": true,
          "notNull": true,
          "autoincrement": true
        },
        "amount": {
          "name": "amount",
          "type": "integer",
          "primaryKey": false,
          "notNull": true,
          "autoincrement": false
        },
        "type": {
          "name": "type",
          "type": "text",
          "primaryKey": false,
          "notNull": true,
          "autoincrement": false
        },
        "metadata": {
          "name": "metadata",
          "type": "text",
          "primaryKey": false,
          "notNull": false,
          "autoincrement": false
        },
        "created_at": {
          "name": "created_at",
          "type": "integer",
          "primaryKey": false,
          "notNull": true,
          "autoincrement": false
        }
      },
      "indexes": {},
      "foreignKeys": {},
      "compositePrimaryKeys": {},
      "uniqueConstraints": {},
      "checkConstraints": {}
    },
    "onboarding_slides": {
      "name": "onboarding_slides",
      "columns": {
        "id": {
          "name": "id",
          "type": "integer",
          "primaryKey": true,
          "notNull": true,
          "autoincrement": true
        },
        "order": {
          "name": "order",
          "type": "integer",
          "primaryKey": false,
          "notNull": true,
          "autoincrement": false
        },
        "icon": {
          "name": "icon",
          "type": "text",
          "primaryKey": false,
          "notNull": true,
          "autoincrement": false
        },
        "title": {
          "name": "title",
          "type": "text",
          "primaryKey": false,
          "notNull": true,
          "autoincrement": false
        },
        "description": {
          "name": "description",
          "type": "text",
          "primaryKey": false,
          "notNull": true,
          "autoincrement": false
        },
        "metadata": {
          "name": "metadata",
          "type": "text",
          "primaryKey": false,
          "notNull": false,
          "autoincrement": false
        },
        "created_at": {
          "name": "created_at",
          "type": "integer",
          "primaryKey": false,
          "notNull": true,
          "autoincrement": false
        }
      },
      "indexes": {},
      "foreignKeys": {},
      "compositePrimaryKeys": {},
      "uniqueConstraints": {},
      "checkConstraints": {}
    }
  },
  "views": {},
  "enums": {},
  "_meta": {
    "schemas": {},
    "tables": {},
    "columns": {}
  },
  "internal": {
    "indexes": {}
  }
}